beartype/__init__.py
beartype/meta.py
beartype/py.typed
beartype/_cave/__init__.py
beartype/_cave/_caveabc.py
beartype/_cave/_cavefast.py
beartype/_cave/_cavemap.py
beartype/_check/__init__.py
beartype/_check/_checksnip.py
beartype/_check/checkmagic.py
beartype/_check/checkmake.py
beartype/_check/code/__init__.py
beartype/_check/code/codemagic.py
beartype/_check/code/codemain.py
beartype/_check/code/codescope.py
beartype/_check/code/_pep/__init__.py
beartype/_check/code/_pep/codepep484604.py
beartype/_check/code/_pep/pep484/__init__.py
beartype/_check/code/_pep/pep484/codepep484typevar.py
beartype/_check/code/_pep/pep484585/__init__.py
beartype/_check/code/_pep/pep484585/codepep484585container.py
beartype/_check/code/_pep/pep484585/codepep484585generic.py
beartype/_check/code/snip/__init__.py
beartype/_check/code/snip/codesnipcls.py
beartype/_check/code/snip/codesnipstr.py
beartype/_check/convert/__init__.py
beartype/_check/convert/_convcoerce.py
beartype/_check/convert/convmain.py
beartype/_check/convert/_reduce/__init__.py
beartype/_check/convert/_reduce/_redmap.py
beartype/_check/convert/_reduce/_redrecurse.py
beartype/_check/convert/_reduce/redmain.py
beartype/_check/convert/_reduce/_nonpep/__init__.py
beartype/_check/convert/_reduce/_nonpep/rednonpeptype.py
beartype/_check/convert/_reduce/_nonpep/api/__init__.py
beartype/_check/convert/_reduce/_nonpep/api/redapinumpy.py
beartype/_check/convert/_reduce/_nonpep/api/redapipandera.py
beartype/_check/convert/_reduce/_pep/__init__.py
beartype/_check/convert/_reduce/_pep/redpep484604.py
beartype/_check/convert/_reduce/_pep/redpep484612646.py
beartype/_check/convert/_reduce/_pep/redpep544.py
beartype/_check/convert/_reduce/_pep/redpep557.py
beartype/_check/convert/_reduce/_pep/redpep585.py
beartype/_check/convert/_reduce/_pep/redpep589.py
beartype/_check/convert/_reduce/_pep/redpep591.py
beartype/_check/convert/_reduce/_pep/redpep593.py
beartype/_check/convert/_reduce/_pep/redpep646.py
beartype-0.22.1.dist-info/METADATA
beartype-0.22.1.dist-info/WHEEL
beartype-0.22.1.dist-info/licenses/LICENSE
beartype-0.22.1.dist-info/RECORD
