Metadata-Version: 2.4
Name: beartype
Version: 0.22.1
Summary: Unbearably fast near-real-time hybrid runtime-static type-checking in pure Python.
Project-URL: Docs, https://beartype.readthedocs.io
Project-URL: GitHub, https://github.com/beartype/beartype
Project-URL: Forums, https://github.com/beartype/beartype/discussions
Project-URL: Issues, https://github.com/beartype/beartype/issues
Project-URL: Releases, https://github.com/beartype/beartype/releases
Author-email: Cecil Curry <leycec@gmail.com>
License: MIT License
License-File: LICENSE
Keywords: annotations,python,type checking,type hints
Classifier: Development Status :: 5 - Production/Stable
Classifier: Intended Audience :: Developers
Classifier: License :: OSI Approved :: MIT License
Classifier: Natural Language :: English
Classifier: Operating System :: OS Independent
Classifier: Programming Language :: Python :: 3
Classifier: Programming Language :: Python :: 3 :: Only
Classifier: Topic :: Software Development :: Code Generators
Classifier: Topic :: Software Development :: Libraries :: Python Modules
Classifier: Topic :: Software Development :: Quality Assurance
Classifier: Typing :: Typed
Requires-Python: >=3.9
Provides-Extra: dev
Requires-Dist: autoapi>=0.9.0; extra == 'dev'
Requires-Dist: celery; extra == 'dev'
Requires-Dist: click; extra == 'dev'
Requires-Dist: coverage>=5.5; extra == 'dev'
Requires-Dist: equinox; (sys_platform == 'linux' and python_version < '3.14.0') and extra == 'dev'
Requires-Dist: fastmcp; (python_version > '3.9.0' and python_version < '3.14.0') and extra == 'dev'
Requires-Dist: jax[cpu]; (sys_platform == 'linux' and python_version < '3.14.0') and extra == 'dev'
Requires-Dist: jaxtyping; (sys_platform == 'linux') and extra == 'dev'
Requires-Dist: langchain; (python_version < '3.14.0' and sys_platform != 'darwin' and platform_python_implementation != 'PyPy') and extra == 'dev'
Requires-Dist: mypy>=0.800; (platform_python_implementation != 'PyPy') and extra == 'dev'
Requires-Dist: nuitka>=1.2.6; (sys_platform == 'linux' and python_version < '3.14.0') and extra == 'dev'
Requires-Dist: numba; (python_version < '3.14.0') and extra == 'dev'
Requires-Dist: numpy; (python_version < '3.14.0' and sys_platform != 'darwin' and platform_python_implementation != 'PyPy') and extra == 'dev'
Requires-Dist: pandera>=0.26.0; (python_version < '3.14.0') and extra == 'dev'
Requires-Dist: polars; (python_version < '3.14.0') and extra == 'dev'
Requires-Dist: pydata-sphinx-theme<=0.7.2; extra == 'dev'
Requires-Dist: pygments; extra == 'dev'
Requires-Dist: pyright>=1.1.370; extra == 'dev'
Requires-Dist: pytest>=4.0.0; extra == 'dev'
Requires-Dist: rich-click; extra == 'dev'
Requires-Dist: setuptools; extra == 'dev'
Requires-Dist: sphinx; extra == 'dev'
Requires-Dist: sphinx<6.0.0,>=4.2.0; extra == 'dev'
Requires-Dist: sphinxext-opengraph>=0.7.5; extra == 'dev'
Requires-Dist: sqlalchemy; extra == 'dev'
Requires-Dist: torch; (sys_platform == 'linux' and python_version < '3.14.0') and extra == 'dev'
Requires-Dist: tox>=3.20.1; extra == 'dev'
Requires-Dist: typer; extra == 'dev'
Requires-Dist: typing-extensions>=3.10.0.0; extra == 'dev'
Requires-Dist: xarray; (python_version < '3.14.0') and extra == 'dev'
Provides-Extra: doc-rtd
Requires-Dist: autoapi>=0.9.0; extra == 'doc-rtd'
Requires-Dist: pydata-sphinx-theme<=0.7.2; extra == 'doc-rtd'
Requires-Dist: setuptools; extra == 'doc-rtd'
Requires-Dist: sphinx<6.0.0,>=4.2.0; extra == 'doc-rtd'
Requires-Dist: sphinxext-opengraph>=0.7.5; extra == 'doc-rtd'
Provides-Extra: test
Requires-Dist: celery; extra == 'test'
Requires-Dist: click; extra == 'test'
Requires-Dist: coverage>=5.5; extra == 'test'
Requires-Dist: equinox; (sys_platform == 'linux' and python_version < '3.14.0') and extra == 'test'
Requires-Dist: fastmcp; (python_version > '3.9.0' and python_version < '3.14.0') and extra == 'test'
Requires-Dist: jax[cpu]; (sys_platform == 'linux' and python_version < '3.14.0') and extra == 'test'
Requires-Dist: jaxtyping; (sys_platform == 'linux') and extra == 'test'
Requires-Dist: langchain; (python_version < '3.14.0' and sys_platform != 'darwin' and platform_python_implementation != 'PyPy') and extra == 'test'
Requires-Dist: mypy>=0.800; (platform_python_implementation != 'PyPy') and extra == 'test'
Requires-Dist: nuitka>=1.2.6; (sys_platform == 'linux' and python_version < '3.14.0') and extra == 'test'
Requires-Dist: numba; (python_version < '3.14.0') and extra == 'test'
Requires-Dist: numpy; (python_version < '3.14.0' and sys_platform != 'darwin' and platform_python_implementation != 'PyPy') and extra == 'test'
Requires-Dist: pandera>=0.26.0; (python_version < '3.14.0') and extra == 'test'
Requires-Dist: polars; (python_version < '3.14.0') and extra == 'test'
Requires-Dist: pygments; extra == 'test'
Requires-Dist: pyright>=1.1.370; extra == 'test'
Requires-Dist: pytest>=4.0.0; extra == 'test'
Requires-Dist: rich-click; extra == 'test'
Requires-Dist: sphinx; extra == 'test'
Requires-Dist: sqlalchemy; extra == 'test'
Requires-Dist: torch; (sys_platform == 'linux' and python_version < '3.14.0') and extra == 'test'
Requires-Dist: tox>=3.20.1; extra == 'test'
Requires-Dist: typer; extra == 'test'
Requires-Dist: typing-extensions>=3.10.0.0; extra == 'test'
Requires-Dist: xarray; (python_version < '3.14.0') and extra == 'test'
Provides-Extra: test-tox
Requires-Dist: celery; extra == 'test-tox'
Requires-Dist: click; extra == 'test-tox'
Requires-Dist: equinox; (sys_platform == 'linux' and python_version < '3.14.0') and extra == 'test-tox'
Requires-Dist: fastmcp; (python_version > '3.9.0' and python_version < '3.14.0') and extra == 'test-tox'
Requires-Dist: jax[cpu]; (sys_platform == 'linux' and python_version < '3.14.0') and extra == 'test-tox'
Requires-Dist: jaxtyping; (sys_platform == 'linux') and extra == 'test-tox'
Requires-Dist: langchain; (python_version < '3.14.0' and sys_platform != 'darwin' and platform_python_implementation != 'PyPy') and extra == 'test-tox'
Requires-Dist: mypy>=0.800; (platform_python_implementation != 'PyPy') and extra == 'test-tox'
Requires-Dist: nuitka>=1.2.6; (sys_platform == 'linux' and python_version < '3.14.0') and extra == 'test-tox'
Requires-Dist: numba; (python_version < '3.14.0') and extra == 'test-tox'
Requires-Dist: numpy; (python_version < '3.14.0' and sys_platform != 'darwin' and platform_python_implementation != 'PyPy') and extra == 'test-tox'
Requires-Dist: pandera>=0.26.0; (python_version < '3.14.0') and extra == 'test-tox'
Requires-Dist: polars; (python_version < '3.14.0') and extra == 'test-tox'
Requires-Dist: pygments; extra == 'test-tox'
Requires-Dist: pyright>=1.1.370; extra == 'test-tox'
Requires-Dist: pytest>=4.0.0; extra == 'test-tox'
Requires-Dist: rich-click; extra == 'test-tox'
Requires-Dist: sphinx; extra == 'test-tox'
Requires-Dist: sqlalchemy; extra == 'test-tox'
Requires-Dist: torch; (sys_platform == 'linux' and python_version < '3.14.0') and extra == 'test-tox'
Requires-Dist: typer; extra == 'test-tox'
Requires-Dist: typing-extensions>=3.10.0.0; extra == 'test-tox'
Requires-Dist: xarray; (python_version < '3.14.0') and extra == 'test-tox'
Provides-Extra: test-tox-coverage
Requires-Dist: coverage>=5.5; extra == 'test-tox-coverage'
